subwhisperer/__init__.py
subwhisperer/cli.py
subwhisperer/core/__init__.py
subwhisperer/core/audio_extractor.py
subwhisperer/core/file_utility.py
subwhisperer/core/segment_detector.py
subwhisperer/core/text_merger.py
subwhisperer/core/transcription_processor.py
subwhisperer/core/whisper_transcriber.py
subwhisperer-1.1.0.dist-info/METADATA
subwhisperer-1.1.0.dist-info/WHEEL
subwhisperer-1.1.0.dist-info/entry_points.txt
subwhisperer-1.1.0.dist-info/top_level.txt
subwhisperer-1.1.0.dist-info/RECORD
