Metadata-Version: 2.4
Name: subwhisperer
Version: 1.1.0
Summary: Generate subtitles (SRT/TXT) from video using OpenAI Whisper.
Author-email: Smarandii <olegsmarandi@gmail.com>
License: MIT
Project-URL: Homepage, https://github.com/Smarandii/subwhisperer
Project-URL: Documentation, https://github.com/Smarandii/subwhisperer#readme
Project-URL: Source, https://github.com/Smarandii/subwhisperer
Keywords: whisper,subtitle,srt,caption,cuda
Classifier: Programming Language :: Python :: 3
Classifier: License :: OSI Approved :: MIT License
Classifier: Environment :: Console
Requires-Python: >=3.12
Requires-Dist: ffmpeg-python>=0.2.0
Requires-Dist: openai-whisper>=20240930
Requires-Dist: pydub>=0.25.1
Requires-Dist: torch==2.6.0
Requires-Dist: torchaudio==2.6.0
Requires-Dist: torchvision==0.21.0
Requires-Dist: transformers>=4.51.3
